{
  "_class": "shapeGroup",
  "booleanOperation": 0,
  "clippingMaskMode": 0,
  "do_objectID": "633CFAED-8BB0-4DAE-8F70-7CC243A90116",
  "exportOptions": {
    "_class": "exportOptions",
    "do_objectID": "EF7D5BF9-918A-4175-95C4-8A53809A93C9",
    "exportFormats": [
    ],
    "includedLayerIds": [
    ],
    "layerOptions": 0,
    "shouldTrim": false
  },
  "frame": {
    "_class": "rect",
    "constrainProportions": false,
    "do_objectID": "660F27F9-5865-4B6A-8C3E-4B0C67B13A23",
    "height": 4.88000000000003,
    "width": 48.42105263157894,
    "x": 21.7894736842105,
    "y": 53.67999999999998
  },
  "hasClickThrough": false,
  "hasClippingMask": false,
  "isFixedToViewport": false,
  "isFlippedHorizontal": false,
  "isFlippedVertical": false,
  "isLocked": false,
  "isVisible": true,
  "layerListExpandedType": 1,
  "layers": [
    {
      "class": "shapePath",
      "id": "29469A66-C9B7-42B6-A95A-AF26DABB4B61"
    }
  ],
  "name": "Line",
  "nameIsFixed": false,
  "resizingConstraint": 63,
  "resizingType": 0,
  "rotation": 0,
  "shouldBreakMaskChain": false,
  "style": {
    "_class": "style",
    "blur": {
      "_class": "blur",
      "center": "{0.5, 0.5}",
      "do_objectID": "1AEEF2E5-E059-4DD3-AF13-B2709A9166A9",
      "isEnabled": false,
      "motionAngle": 0,
      "radius": 20,
      "type": 0
    },
    "borderOptions": {
      "_class": "borderOptions",
      "dashPattern": [
      ],
      "do_objectID": "AFA94047-2C15-4548-9BB3-149B91A4ABB7",
      "isEnabled": false,
      "lineCapStyle": 1,
      "lineJoinStyle": 0
    },
    "borders": [
      {
        "_class": "border",
        "color": {
          "_class": "color",
          "alpha": 1,
          "blue": 0.8156862854957581,
          "green": 0.7607843279838562,
          "red": 0.7333333492279053
        },
        "fillType": 0,
        "isEnabled": true,
        "position": 0,
        "thickness": 4
      }
    ],
    "do_objectID": "35B188B7-86B7-430E-BDEC-5D63D114F8CF",
    "endMarkerType": 0,
    "fills": [
      {
        "_class": "fill",
        "color": {
          "_class": "color",
          "alpha": 1,
          "blue": 0.847,
          "green": 0.847,
          "red": 0.847
        },
        "fillType": 0,
        "isEnabled": false,
        "noiseIndex": 0,
        "noiseIntensity": 0,
        "patternFillType": 1,
        "patternTileScale": 1
      }
    ],
    "miterLimit": 10,
    "startMarkerType": 0,
    "windingRule": 1
  },
  "windingRule": 1
}