{
  "_class": "text",
  "attributedString": {
    "_class": "attributedString",
    "attributes": [
      {
        "_class": "stringAttribute",
        "attributes": {
          "MSAttributedStringColorAttribute": {
            "_class": "color",
            "alpha": 1,
            "blue": 0.7093962585,
            "green": 0.6505690816,
            "red": 0.621155582
          },
          "MSAttributedStringFontAttribute": {
            "_class": "fontDescriptor",
            "attributes": {
              "name": "NunitoSans-Regular",
              "size": 36
            }
          },
          "kerning": 0,
          "paragraphStyle": {
            "_class": "paragraphStyle",
            "alignment": 2,
            "allowsDefaultTighteningForTruncation": 0,
            "maximumLineHeight": 48,
            "minimumLineHeight": 48
          }
        },
        "length": 277,
        "location": 0
      }
    ],
    "string": "Centralized scholarly communication is one of the absurd obstacles in research community. \nBeginning with decentralizing it, Pluto aims to remove any barriers in science, \nto enable anyone to fully realize potential as a scientist, and to accelerate the advancement of science."
  },
  "automaticallyDrawOnUnderlyingPath": false,
  "booleanOperation": 0,
  "do_objectID": "007E9EAF-8920-49E2-A9C3-3758155E3E20",
  "dontSynchroniseWithSymbol": false,
  "exportOptions": {
    "_class": "exportOptions",
    "do_objectID": "394D3D7D-911F-43AA-82B8-C06F9DAF0E52",
    "exportFormats": [
    ],
    "includedLayerIds": [
    ],
    "layerOptions": 0,
    "shouldTrim": false
  },
  "frame": {
    "_class": "rect",
    "constrainProportions": false,
    "do_objectID": "C0916C5F-A72B-445A-BF6C-6AC32B58572C",
    "height": 144,
    "width": 1794,
    "x": 303,
    "y": 753
  },
  "glyphBounds": "{{83, 10}, {1626, 129}}",
  "isFixedToViewport": false,
  "isFlippedHorizontal": false,
  "isFlippedVertical": false,
  "isLocked": false,
  "isVisible": true,
  "layerListExpandedType": 0,
  "lineSpacingBehaviour": 2,
  "name": "Centralized scholarl",
  "nameIsFixed": false,
  "resizingConstraint": 47,
  "resizingType": 0,
  "rotation": 0,
  "shouldBreakMaskChain": false,
  "style": {
    "_class": "style",
    "blur": {
      "_class": "blur",
      "center": "{0.5, 0.5}",
      "do_objectID": "BEEB154B-FE67-4002-8C5E-454DBC6429D5",
      "isEnabled": false,
      "motionAngle": 0,
      "radius": 24,
      "type": 0
    },
    "do_objectID": "2B397BCA-1D4B-4132-94C8-876605CEDEE4",
    "endMarkerType": 0,
    "miterLimit": 10,
    "startMarkerType": 0,
    "textStyle": {
      "_class": "textStyle",
      "do_objectID": "D58AA37C-4233-47D1-B52A-3EEE2FF3E74E",
      "encodedAttributes": {
        "MSAttributedStringColorAttribute": {
          "_class": "color",
          "alpha": 1,
          "blue": 0.7093962585,
          "green": 0.6505690816,
          "red": 0.621155582
        },
        "MSAttributedStringFontAttribute": {
          "_class": "fontDescriptor",
          "attributes": {
            "name": "NunitoSans-Regular",
            "size": 36
          }
        },
        "kerning": 0,
        "paragraphStyle": {
          "_class": "paragraphStyle",
          "alignment": 2,
          "allowsDefaultTighteningForTruncation": 0,
          "maximumLineHeight": 48,
          "minimumLineHeight": 48
        }
      },
      "verticalAlignment": 0
    },
    "windingRule": 1
  },
  "textBehaviour": 1,
  "userInfo": {
    "com.animaapp.stc-sketch-plugin": {
      "kModelPropertiesKey": {
        "isAutoWidth": 0
      }
    }
  }
}